hydra_plugins/experiment_sweeper_plugin/__init__.py
hydra_plugins/experiment_sweeper_plugin/experiment_sweeper.py
hydra_experiment_sweeper-0.1.1.dist-info/LICENSE
hydra_experiment_sweeper-0.1.1.dist-info/WHEEL
hydra_experiment_sweeper-0.1.1.dist-info/METADATA
hydra_experiment_sweeper-0.1.1.dist-info/RECORD
