Metadata-Version: 2.1
Name: hydra-experiment-sweeper
Version: 0.1.1
Summary: A hydra sweeper with configurable overrides for reproducible experiments
Author-email: Marten Lienen <marten.lienen@gmail.com>
Requires-Python: >= 3.8
Classifier: Development Status :: 3 - Alpha
Classifier: Intended Audience :: Developers
Classifier: License :: OSI Approved :: MIT License
Classifier: Operating System :: OS Independent
Classifier: Programming Language :: Python
Requires-Dist: hydra-core
Requires-Dist: more-itertools
Requires-Dist: pytest ; extra == "test"
Project-URL: homepage, https://github.com/martenlienen/hydra-experiment-sweeper
Provides-Extra: test
